battlesim/__defaults.py
battlesim/__init__.py
battlesim/__legacy.py
battlesim/_ai.py
battlesim/_battle.py
battlesim/_damage.py
battlesim/_distributions.py
battlesim/_hit.py
battlesim/_jitcode.py
battlesim/_mathutils.py
battlesim/_move.py
battlesim/_simulator_fast.py
battlesim/_target.py
battlesim/_terrain.py
battlesim/_unit_quant.py
battlesim/_utils.py
battlesim/utils.py
battlesim/distrib/__init__.py
battlesim/distrib/_composite.py
battlesim/distrib/_distrib2.py
battlesim/plot/__init__.py
battlesim/plot/_imageplot.py
battlesim/plot/_simplot.py
battlesim/simulation/__init__.py
battlesim/simulation/_ai.py
battlesim/simulation/_damage.py
battlesim/simulation/_hit.py
battlesim/simulation/_move.py
battlesim/simulation/_simulator_fast.py
battlesim/simulation/_target.py
battlesim/terra/__init__.py
battlesim/terra/_noise.py
battlesim/terra/_terrain.py
battlesim-0.3.7.dist-info/LICENSE.txt
battlesim-0.3.7.dist-info/METADATA
battlesim-0.3.7.dist-info/WHEEL
battlesim-0.3.7.dist-info/top_level.txt
battlesim-0.3.7.dist-info/RECORD
