Metadata-Version: 2.1
Name: battlesim
Version: 0.3.7
Summary: A python package for simulating battles and visualizing them in animation
Home-page: https://github.com/gregparkes/battlesim
Author: Gregory Parkes
Author-email: gregorymparkes@gmail.com
License: GPL-3.0
Platform: UNKNOWN
Classifier: Natural Language :: English
Classifier: Programming Language :: Python :: 3.8
Classifier: Intended Audience :: Science/Research
Classifier: Intended Audience :: Developers
Classifier: License :: OSI Approved :: GNU General Public License v3 (GPLv3)
Classifier: Framework :: IPython
Classifier: Framework :: Jupyter
Classifier: Development Status :: 3 - Alpha
Classifier: Intended Audience :: Science/Research
Classifier: Topic :: Scientific/Engineering
Requires-Python: >=3.8
License-File: LICENSE.txt
Requires-Dist: numpy (>=1.11.0)
Requires-Dist: pandas (>=0.25.1)
Requires-Dist: matplotlib (>=3.1.1)
Requires-Dist: numba (>=0.45)
